f2py_jit/__init__.py
f2py_jit/f2py_jit.py
f2py_jit/finline.py
f2py_jit-1.2.1.dist-info/licenses/LICENSE
f2py_jit-1.2.1.dist-info/METADATA
f2py_jit-1.2.1.dist-info/WHEEL
f2py_jit-1.2.1.dist-info/top_level.txt
f2py_jit-1.2.1.dist-info/RECORD
