Metadata-Version: 2.4
Name: f2py-jit
Version: 1.2.1
Summary: Just-in-time Fortran extension builder for Python
Author-email: Daniele Coslovich <daniele.coslovich@umontpellier.fr>
License: GPLv3
Project-URL: repository, https://framagit.org/coslo/f2py-jit
Project-URL: homepage, https://framagit.org/coslo/f2py-jit
Project-URL: documentation, https://coslo.frama.io/f2py-jit
Classifier: License :: OSI Approved :: GNU General Public License v3 (GPLv3)
Classifier: Development Status :: 5 - Production/Stable
Classifier: Programming Language :: Python :: 3
Classifier: Programming Language :: Python :: 3.7
Classifier: Programming Language :: Python :: 3.8
Classifier: Programming Language :: Python :: 3.9
Classifier: Programming Language :: Python :: 3.10
Classifier: Programming Language :: Python :: 3.11
Classifier: Programming Language :: Python :: 3.12
Classifier: Programming Language :: Python :: 3.13
Requires-Python: >=3.7
License-File: LICENSE
Requires-Dist: numpy
Requires-Dist: setuptools<74; python_version >= "3.8"
Requires-Dist: setuptools; python_version < "3.8"
Requires-Dist: meson; python_version >= "3.11"
Requires-Dist: meson-python; python_version >= "3.11"
Requires-Dist: ninja; python_version >= "3.11"
Provides-Extra: types
Requires-Dist: f90wrap~=0.2.12; extra == "types"
Dynamic: license-file
